oasees_test_sdk/cli/cli.py
oasees_test_sdk/cli/cli2.py
oasees_test_sdk/cli/ipfs_client.py
oasees_test_sdk/cli/oasees_ml_ops.py
oasees_test_sdk/oasees_sdk/__init__.py
oasees_test_sdk/oasees_sdk/cluster_ipfs_upload.py
oasees_test_sdk/oasees_sdk/deploy_pipeline.py
oasees_test_sdk/oasees_sdk/mlops/__init__.py
oasees_test_sdk/oasees_sdk/mlops/env_vars.py
oasees_test_sdk/oasees_sdk/mlops/ml_template.py
oasees_test_sdk/oasees_sdk/mlops/templating_functions.py
oasees_test_sdk/oasees_sdk/mlops/util_files.py
oasees_test_sdk/oasees_sdk/sdk.py
oasees_test_sdk/oasees_sdk/training_workload.py
oasees_test_sdk/oasees_sdk/utility_functions.py
oasees_test_sdk-0.4.6.dist-info/METADATA
oasees_test_sdk-0.4.6.dist-info/WHEEL
oasees_test_sdk-0.4.6.dist-info/entry_points.txt
oasees_test_sdk-0.4.6.dist-info/RECORD
