Metadata-Version: 2.3
Name: oasees_test_sdk
Version: 0.4.6
Summary: test Oasees SDK
Author: Achilleas Economopoulos
Classifier: License :: OSI Approved :: MIT License
Classifier: Operating System :: OS Independent
Classifier: Programming Language :: Python :: 2
Classifier: Programming Language :: Python :: 2.7
Classifier: Programming Language :: Python :: 3
Classifier: Programming Language :: Python :: 3.4
Classifier: Programming Language :: Python :: 3.5
Classifier: Programming Language :: Python :: 3.6
Classifier: Programming Language :: Python :: 3.7
Classifier: Programming Language :: Python :: 3.8
Classifier: Programming Language :: Python :: 3.9
Classifier: Programming Language :: Python :: 3.10
Classifier: Programming Language :: Python :: 3.11
Classifier: Programming Language :: Python :: 3.12
Classifier: Programming Language :: Python :: 3.13
Requires-Dist: Click
Requires-Dist: ipfshttpclient (==0.8.0a2)
Requires-Dist: kubernetes
Requires-Dist: python-dotenv
Requires-Dist: requests
Requires-Dist: requests_toolbelt
Requires-Dist: soorgeon
Requires-Dist: web3 (==6.19.0)
